zypl_macro/__init__.py
zypl_macro/library.py
zypl_macro-1.0.5.dist-info/LICENSE
zypl_macro-1.0.5.dist-info/METADATA
zypl_macro-1.0.5.dist-info/WHEEL
zypl_macro-1.0.5.dist-info/top_level.txt
zypl_macro-1.0.5.dist-info/RECORD
