Metadata-Version: 2.1
Name: zypl-macro
Version: 1.0.5
Summary: zypl.ai alternative data API interface lib
Author: Me
Classifier: Programming Language :: Python :: 3
Classifier: License :: OSI Approved :: MIT License
Classifier: Operating System :: OS Independent
Requires-Python: >=3.0
License-File: LICENSE
Requires-Dist: pandas (>=1.5.3)
Requires-Dist: requests (>=2.28.2)
